modpypes/__init__.py
modpypes/app.py
modpypes/client.py
modpypes/pdu.py
modpypes/server.py
modpypes-0.2.12.dist-info/DESCRIPTION.rst
modpypes-0.2.12.dist-info/METADATA
modpypes-0.2.12.dist-info/RECORD
modpypes-0.2.12.dist-info/WHEEL
modpypes-0.2.12.dist-info/metadata.json
modpypes-0.2.12.dist-info/top_level.txt
