Metadata-Version: 2.0
Name: modpypes
Version: 0.2.12
Summary: Python library for MODBUS based on BACpypes
Home-page: https://github.com/JoelBender/modpypes
Author: Joel Bender
Author-email: joel@carrickbender.com
License: MIT
Keywords: modpypes
Platform: UNKNOWN
Classifier: Development Status :: 5 - Production/Stable
Classifier: Intended Audience :: Developers
Classifier: License :: OSI Approved :: BSD License
Classifier: Natural Language :: English
Classifier: Programming Language :: Python :: 2
Classifier: Programming Language :: Python :: 2.7
Classifier: Programming Language :: Python :: 3
Classifier: Programming Language :: Python :: 3.4
Classifier: Programming Language :: Python :: 3.5
Classifier: Topic :: Software Development :: Libraries :: Python Modules
Classifier: Topic :: System :: Networking
Classifier: Topic :: Utilities
Requires-Dist: bacpypes
